setup.py
hdsubnetfinder/__init__.py
hdsubnetfinder.egg-info/PKG-INFO
hdsubnetfinder.egg-info/SOURCES.txt
hdsubnetfinder.egg-info/dependency_links.txt
hdsubnetfinder.egg-info/pbr.json
hdsubnetfinder.egg-info/requires.txt
hdsubnetfinder.egg-info/top_level.txt
hdsubnetfinder/kernel/__init__.py
hdsubnetfinder/kernel/kernel.py
hdsubnetfinder/kernel/kernel_generator.py
hdsubnetfinder/kernel/kernel_util.py
hdsubnetfinder/subnetwork/__init__.py
hdsubnetfinder/subnetwork/network_util.py
hdsubnetfinder/subnetwork/sub_network_finder.py
tests/__init__.py
tests/test_kernel.py
tests/test_kernel_generator.py
tests/test_network_util.py
tests/test_sub_network_finder.py
tests/resource/__init__.py