Metadata-Version: 1.1
Name: hdsubnetfinder
Version: 0.2.1
Summary: Heat Diffusion Sub-network Finder
Home-page: https://github.com/idekerlab/hdsubnetfinder
Author: Daniel Carlin, Keiichiro Ono
Author-email: kono@ucsd.edu
License: MIT License
Keywords: bioinformatics,graph,network,cytoscape
Platform: UNKNOWN
Classifier: Intended Audience :: Science/Research
Classifier: Intended Audience :: Developers
Classifier: Operating System :: OS Independent
Classifier: Development Status :: 3 - Alpha
Classifier: Programming Language :: Python :: 2.7
Classifier: License :: OSI Approved :: MIT License
Classifier: Topic :: Scientific/Engineering :: Bio-Informatics
Classifier: Topic :: Scientific/Engineering :: Information Analysis
Classifier: Topic :: Scientific/Engineering :: Mathematics
